ps_database/__init__.py
ps_database/database code.py
pritesh_db_connection-0.0.1.dist-info/METADATA
pritesh_db_connection-0.0.1.dist-info/WHEEL
pritesh_db_connection-0.0.1.dist-info/top_level.txt
pritesh_db_connection-0.0.1.dist-info/RECORD
